pyenet_sc/__init__.py
pyenet_sc/main.py
pyenet_sc-0.3.dist-info/LICENSE
pyenet_sc-0.3.dist-info/METADATA
pyenet_sc-0.3.dist-info/WHEEL
pyenet_sc-0.3.dist-info/top_level.txt
pyenet_sc-0.3.dist-info/RECORD
