Metadata-Version: 2.1
Name: pyenet-sc
Version: 0.3
License-File: LICENSE
Requires-Dist: pyenet>=1.3.17
